LeXmo/LeXmo.py
LeXmo/__init__.py
LeXmo-0.1.4.dist-info/LICENSE
LeXmo-0.1.4.dist-info/METADATA
LeXmo-0.1.4.dist-info/WHEEL
LeXmo-0.1.4.dist-info/top_level.txt
LeXmo-0.1.4.dist-info/RECORD
